symbolmachines/__init__.py
symbolmachines/client.py
symbolmachines-0.1.1.dist-info/METADATA
symbolmachines-0.1.1.dist-info/WHEEL
symbolmachines-0.1.1.dist-info/top_level.txt
symbolmachines-0.1.1.dist-info/RECORD
