Metadata-Version: 2.4
Name: symbolmachines
Version: 0.1.1
Summary: Symbol Machines Memory SDK — Long-term cognitive memory for any LLM.
Author-email: Symbol Machines <joe@symbolmachines.com>
License: MIT
Project-URL: Homepage, https://symbolmachines.com
Project-URL: Repository, https://github.com/cojohen/symbol-sdk
Keywords: LLM,memory,knowledge-graph,symbol-machines,AI,AGI
Classifier: Programming Language :: Python :: 3
Classifier: License :: OSI Approved :: MIT License
Classifier: Operating System :: OS Independent
Requires-Python: >=3.8
Requires-Dist: requests>=2.25
